stimuli/__init__.py
stimuli/_version.py
stimuli/audio/__init__.py
stimuli/audio/_base.py
stimuli/audio/am.py
stimuli/audio/noise.py
stimuli/audio/sound.py
stimuli/audio/tone.py
stimuli/audio/backend/__init__.py
stimuli/audio/backend/_base.py
stimuli/audio/backend/sounddevice.py
stimuli/commands/__init__.py
stimuli/commands/main.py
stimuli/commands/sys_info.py
stimuli/keyboard/__init__.py
stimuli/keyboard/_keyboard.py
stimuli/keyboard/_utils.py
stimuli/time/__init__.py
stimuli/time/_clock.py
stimuli/time/_sleep.py
stimuli/trigger/__init__.py
stimuli/trigger/_base.py
stimuli/trigger/lsl.py
stimuli/trigger/mock.py
stimuli/trigger/parallel.py
stimuli/trigger/_io/__init__.py
stimuli/trigger/_io/_dlportio.py
stimuli/trigger/_io/_inpout.py
stimuli/trigger/_io/_linux.py
stimuli/utils/__init__.py
stimuli/utils/_checks.py
stimuli/utils/_docs.py
stimuli/utils/_fixes.py
stimuli/utils/_imports.py
stimuli/utils/config.py
stimuli/utils/logs.py
stimuli-1.1.0.dist-info/licenses/LICENSE
stimuli-1.1.0.dist-info/METADATA
stimuli-1.1.0.dist-info/WHEEL
stimuli-1.1.0.dist-info/entry_points.txt
stimuli-1.1.0.dist-info/top_level.txt
stimuli-1.1.0.dist-info/RECORD
